handle_intro/__init__.py
handle_intro/api.py
handle_intro/application.py
handle_intro/get_event.py
handle_intro/handler.py
handle_intro/sample_events.py
handle_intro/controllers/base_controller.py
handle_intro/controllers/handle_intro_controller.py
handle_intro/factories/base_factory.py
handle_intro/factories/factory.py
handle_intro/infra/aws_request.py
handle_intro/infra/rest.py
handle_intro/infra/script.py
handle_intro/infra/handle_intro/handle_intro.py
handle_intro/models/ad.py
handle_intro/models/intro.py
handle_intro/models/page.py
handle_intro/models/request.py
handle_intro/models/response.py
handle_intro/models/saved_file.py
handle_intro/models/video.py
handle_intro/services/base_service.py
handle_intro/services/handle_intro_service.py
handle_intro/services/speech_service.py
handle_intro/services/text_utils_service.py
handle_intro/services/time_service.py
handle_intro/utils/file.py
handle_intro/utils/helpers.py
handle_intro/utils/html.py
handle_intro/utils/json.py
handle_intro/utils/lambda_helpers.py
handle_intro/utils/markdown.py
handle_intro/utils/service_helper.py
handle_intro/utils/string_utils.py
handle_intro/utils/text.py
handle_intro/utils/time.py
handle_intro/utils/url.py
handle_intro/utils/video.py
video_bot_handle_intro-0.0.2.dist-info/LICENSE
video_bot_handle_intro-0.0.2.dist-info/METADATA
video_bot_handle_intro-0.0.2.dist-info/WHEEL
video_bot_handle_intro-0.0.2.dist-info/top_level.txt
video_bot_handle_intro-0.0.2.dist-info/RECORD
